extract360/__init__.py
extract360/client.py
extract360-0.2.0.dist-info/licenses/LICENSE
extract360-0.2.0.dist-info/METADATA
extract360-0.2.0.dist-info/WHEEL
extract360-0.2.0.dist-info/top_level.txt
extract360-0.2.0.dist-info/RECORD
