Metadata-Version: 2.4
Name: extract360
Version: 0.2.0
Summary: Official Python client for the Extract360 API.
Home-page: https://extract360.tech
Author: Extract360
Author-email: Extract360 <contato@extract360.tech>
Project-URL: Homepage, https://extract360.tech
Project-URL: Repository, https://github.com/synkia/extract360
Project-URL: Issues, https://github.com/synkia/extract360/issues
Keywords: extract360,web-scraping,sdk,api-client
Classifier: Development Status :: 4 - Beta
Classifier: Intended Audience :: Developers
Classifier: Programming Language :: Python
Classifier: Programming Language :: Python :: 3
Classifier: Programming Language :: Python :: 3.9
Classifier: Programming Language :: Python :: 3.10
Classifier: Programming Language :: Python :: 3.11
Classifier: Programming Language :: Python :: 3.12
Classifier: Programming Language :: Python :: 3.13
Classifier: Topic :: Software Development :: Libraries
Classifier: Topic :: Internet :: WWW/HTTP
Requires-Python: >=3.9
License-File: LICENSE
Requires-Dist: requests>=2.31
Dynamic: author
Dynamic: home-page
Dynamic: license-file
Dynamic: requires-python
